proof_of_weights/__init__.py
proof_of_weights/main.py
proof_of_weights-0.0.5.dist-info/METADATA
proof_of_weights-0.0.5.dist-info/WHEEL
proof_of_weights-0.0.5.dist-info/top_level.txt
proof_of_weights-0.0.5.dist-info/RECORD
