Metadata-Version: 2.1
Name: proof-of-weights
Version: 0.0.5
Summary: SDK for validators from various subnets to publish their reward function inputs to validators within the omron subnet.
Home-page: https://github.com/inference-labs-inc/proof-of-weights-sdk
Classifier: Programming Language :: Python :: 3
Classifier: Development Status :: 1 - Planning
Requires: requests
Requires: bittensor
Requires: yarl
Requires-Python: >3.6
